LICENSE
MANIFEST.in
README.md
README.rst
setup.cfg
setup.py
pygrok/__init__.py
pygrok/pygrok.py
pygrok.egg-info/PKG-INFO
pygrok.egg-info/SOURCES.txt
pygrok.egg-info/dependency_links.txt
pygrok.egg-info/requires.txt
pygrok.egg-info/top_level.txt
pygrok/patterns/firewalls
pygrok/patterns/grok-patterns
pygrok/patterns/haproxy
pygrok/patterns/java
pygrok/patterns/junos
pygrok/patterns/linux-syslog
pygrok/patterns/mcollective
pygrok/patterns/mcollective-patterns
pygrok/patterns/nagios
pygrok/patterns/postgresql
pygrok/patterns/redis
pygrok/patterns/ruby
tests/test_pygrok.py