Metadata-Version: 1.1
Name: pygrok
Version: 0.5.0
Summary: A Python library to parse strings and extract information from structured/unstructured data
Home-page: https://github.com/garyelephant/pygrok
Author: garyelephant
Author-email: garygaowork@gmail.com
License: MIT
Download-URL: https://github.com/garyelephant/pygrok/tarball/v0.5.0
Keywords: python grok,regex
Platform: UNKNOWN
